odoo/addons/website_sale_slides_order_line_link/README.rst
odoo/addons/website_sale_slides_order_line_link/__init__.py
odoo/addons/website_sale_slides_order_line_link/__manifest__.py
odoo/addons/website_sale_slides_order_line_link/description/icon.png
odoo/addons/website_sale_slides_order_line_link/description/index.html
odoo/addons/website_sale_slides_order_line_link/i18n/it.po
odoo/addons/website_sale_slides_order_line_link/i18n/website_sale_slides_order_line_link.pot
odoo/addons/website_sale_slides_order_line_link/models/__init__.py
odoo/addons/website_sale_slides_order_line_link/models/sale_order.py
odoo/addons/website_sale_slides_order_line_link/models/slide_channel.py
odoo/addons/website_sale_slides_order_line_link/readme/CONTRIBUTORS.md
odoo/addons/website_sale_slides_order_line_link/readme/DESCRIPTION.md
odoo/addons/website_sale_slides_order_line_link/readme/USAGE.md
odoo/addons/website_sale_slides_order_line_link/static/description/icon.png
odoo/addons/website_sale_slides_order_line_link/static/description/index.html
odoo/addons/website_sale_slides_order_line_link/tests/__init__.py
odoo/addons/website_sale_slides_order_line_link/tests/test_website_sale_slides_order_line_link.py
odoo_addon_website_sale_slides_order_line_link-17.0.1.0.0.4.dist-info/METADATA
odoo_addon_website_sale_slides_order_line_link-17.0.1.0.0.4.dist-info/WHEEL
odoo_addon_website_sale_slides_order_line_link-17.0.1.0.0.4.dist-info/top_level.txt
odoo_addon_website_sale_slides_order_line_link-17.0.1.0.0.4.dist-info/RECORD
